{
  "fileName": "fullscreenQuad.js",
  "filePath": "src/scene/shader-lib/chunks/common/vert/fullscreenQuad.js",
  "url": "https://github.com/playcanvas/engine/src/scene/shader-lib/chunks/common/vert/fullscreenQuad.js",
  "summary": "The code above is a GLSL shader code that is used to render 2D graphics in the PlayCanvas engine. The purpose of this code is to define the vertex position and the texture coordinates of a 2D object that is being rendered on the screen. \n\nThe `attribute vec2 vertex_position` defines the position of the vertex in 2D space. The `varying vec2 vUv0` is used to pass the texture coordinates to the fragment shader. \n\nThe `gl_Position` variable is used to set the position of the vertex in 3D space. In this case, it is set to `vec4(vertex_position, 0.5, 1.0)` which means that the vertex is positioned at `vertex_position` in the x and y axis, and at 0.5 in the z axis. The w component is set to 1.0 which means that it is not a directional vector.\n\nThe `vUv0` variable is used to set the texture coordinates of the vertex. It is calculated by multiplying the vertex position by 0.5 and adding 0.5 to it. This ensures that the texture coordinates are in the range of 0 to 1, which is required by the fragment shader.\n\nThis code is used in the larger PlayCanvas engine project to render 2D graphics on the screen. It is used in conjunction with other GLSL shader codes and JavaScript code to create complex 2D and 3D scenes. \n\nHere is an example of how this code can be used in a JavaScript file:\n\n```javascript\nconst shader = new pc.Shader(device, {\n    attributes: {\n        vertex_position: pc.SEMANTIC_POSITION\n    },\n    vshader: /* glsl */`\n        attribute vec2 vertex_position;\n\n        varying vec2 vUv0;\n\n        void main(void)\n        {\n            gl_Position = vec4(vertex_position, 0.5, 1.0);\n            vUv0 = vertex_position.xy*0.5+0.5;\n        }\n    `,\n    fshader: /* glsl */`\n        uniform sampler2D texture_map;\n\n        varying vec2 vUv0;\n\n        void main(void)\n        {\n            gl_FragColor = texture2D(texture_map, vUv0);\n        }\n    `\n});\n```\n\nIn this example, the GLSL shader code is used to create a new `pc.Shader` object that is used to render a texture on a 2D object. The `vshader` property of the `pc.Shader` object is set to the GLSL shader code above. The `fshader` property is set to another GLSL shader code that is used to render the texture on the object. \n\nOverall, this GLSL shader code is an essential part of the PlayCanvas engine project that is used to render 2D graphics on the screen.",
  "questions": "1. What is the purpose of the `vertex_position` attribute in this code?\n   - The `vertex_position` attribute is used to define the position of each vertex in the shader program.\n\n2. What does the `vUv0` varying variable represent?\n   - The `vUv0` varying variable represents the texture coordinates of the vertex.\n\n3. What is the significance of the `/* glsl */` comment at the beginning of the code?\n   - The `/* glsl */` comment indicates that the code is written in GLSL (OpenGL Shading Language) format, which is a high-level language used to write shaders for graphics processing units (GPUs)."
}