{
  "fileName": "uv1.js",
  "filePath": "src/scene/shader-lib/chunks/lit/vert/uv1.js",
  "url": "https://github.com/playcanvas/engine/src/scene/shader-lib/chunks/lit/vert/uv1.js",
  "summary": "The code above is a GLSL shader function that returns a 2D vector representing the texture coordinates of a vertex. The function is named `getUv1()` and is exported as the default function of the module. \n\nIn the PlayCanvas engine, shaders are used to define how 3D models are rendered on the screen. This particular shader function is used to retrieve the texture coordinates of a vertex, which are used to map a 2D texture onto a 3D model. \n\nThe function takes no arguments and simply returns the `vertex_texCoord1` variable, which is assumed to be a 2D vector representing the texture coordinates of the vertex. \n\nHere is an example of how this function might be used in a PlayCanvas shader:\n\n```glsl\nuniform sampler2D texture;\nvarying vec2 vUv1;\n\nvoid main() {\n    vec4 color = texture2D(texture, vUv1);\n    gl_FragColor = color;\n}\n```\n\nIn this example, the `getUv1()` function is used to retrieve the texture coordinates of each vertex and pass them to the fragment shader as a varying variable named `vUv1`. The fragment shader then uses these texture coordinates to sample the texture and set the color of the pixel being rendered. \n\nOverall, this code is a small but important part of the PlayCanvas engine's rendering pipeline, allowing developers to easily map textures onto 3D models.",
  "questions": "1. What is the purpose of this code?\n   - This code exports a GLSL function that returns a vec2 representing the texture coordinates of a vertex.\n\n2. How is this code used within the PlayCanvas engine?\n   - It is unclear from this code alone how it is used within the PlayCanvas engine. It may be used as part of a shader program or in some other context.\n\n3. Are there any dependencies or requirements for using this code?\n   - It is unclear from this code alone if there are any dependencies or requirements for using it. It may require certain libraries or be dependent on other code within the PlayCanvas engine."
}